AlgoGraph/__init__.py
AlgoGraph/builder.py
AlgoGraph/edge.py
AlgoGraph/graph.py
AlgoGraph/graph_selectors.py
AlgoGraph/interop.py
AlgoGraph/query.py
AlgoGraph/serialization.py
AlgoGraph/transformers.py
AlgoGraph/vertex.py
AlgoGraph/views.py
AlgoGraph/visualization.py
AlgoGraph/algorithms/__init__.py
AlgoGraph/algorithms/centrality.py
AlgoGraph/algorithms/coloring.py
AlgoGraph/algorithms/connectivity.py
AlgoGraph/algorithms/flow.py
AlgoGraph/algorithms/matching.py
AlgoGraph/algorithms/shortest_path.py
AlgoGraph/algorithms/spanning_tree.py
AlgoGraph/algorithms/traversal.py
AlgoGraph/shell/__init__.py
AlgoGraph/shell/cli.py
AlgoGraph/shell/commands.py
AlgoGraph/shell/context.py
AlgoGraph/shell/shell.py
algograph-2.1.0.dist-info/METADATA
algograph-2.1.0.dist-info/WHEEL
algograph-2.1.0.dist-info/entry_points.txt
algograph-2.1.0.dist-info/top_level.txt
algograph-2.1.0.dist-info/RECORD
