Metadata-Version: 2.4
Name: AlgoGraph
Version: 2.1.0
Summary: Immutable graph library with 56+ algorithms, transformers, selectors, and lazy views
Author-email: Alex Towell <lex@metafunctor.com>
Maintainer-email: Alex Towell <lex@metafunctor.com>
License: MIT
Project-URL: Homepage, https://github.com/queelius/AlgoGraph
Project-URL: Documentation, https://queelius.github.io/AlgoGraph/
Project-URL: Repository, https://github.com/queelius/AlgoGraph
Project-URL: Bug Tracker, https://github.com/queelius/AlgoGraph/issues
Project-URL: Changelog, https://github.com/queelius/AlgoGraph/releases
Keywords: graph,algorithms,data-structures,immutable,networkx,graph-theory
Classifier: Development Status :: 4 - Beta
Classifier: Intended Audience :: Developers
Classifier: Intended Audience :: Science/Research
Classifier: License :: OSI Approved :: MIT License
Classifier: Operating System :: OS Independent
Classifier: Programming Language :: Python :: 3
Classifier: Programming Language :: Python :: 3.8
Classifier: Programming Language :: Python :: 3.9
Classifier: Programming Language :: Python :: 3.10
Classifier: Programming Language :: Python :: 3.11
Classifier: Programming Language :: Python :: 3.12
Classifier: Topic :: Scientific/Engineering
Classifier: Topic :: Scientific/Engineering :: Mathematics
Classifier: Topic :: Software Development :: Libraries :: Python Modules
Classifier: Typing :: Typed
Requires-Python: >=3.8
Provides-Extra: dev
Requires-Dist: pytest>=7.0; extra == "dev"
Requires-Dist: pytest-cov>=4.0; extra == "dev"
Requires-Dist: mkdocs>=1.5; extra == "dev"
Requires-Dist: mkdocs-material>=9.0; extra == "dev"
Provides-Extra: algotree
Requires-Dist: AlgoTree>=1.0; extra == "algotree"
